procslib-0.7.1.dist-info/METADATA
procslib-0.7.1.dist-info/WHEEL
procslib-0.7.1.dist-info/entry_points.txt
procslib-0.7.1.dist-info/licenses/LICENSE
procslib/__init__.py
procslib/__main__.py
procslib/cli.py
procslib/config.py
procslib/debug.py
procslib/model_builder.py
procslib/model_registry.py
procslib/models/__init__.py
procslib/models/_clip_aesthetic_cached.py
procslib/models/_convnext_v2.py
procslib/models/_legacy/anime_aesthetic.py
procslib/models/_legacy/anime_aesthetic_cls.py
procslib/models/_legacy/legacy_registry.py
procslib/models/_legacy/q_align.py
procslib/models/_legacy/vila_wrapper.py
procslib/models/base_inference.py
procslib/models/clip_aesthetic_cached.py
procslib/models/complexity_ic9600.py
procslib/models/cv2_wrapper.py
procslib/models/depth_wrapper.py
procslib/models/hf_automodel_inference.py
procslib/models/laion_watermark.py
procslib/models/novelai_wrapper.py
procslib/models/pixiv_compound_score.py
procslib/models/rtmpose.py
procslib/models/siglip_aesthetics.py
procslib/models/style_cls_simsiam.py
procslib/models/tagger_camie.py
procslib/models/tagger_jz.py
procslib/models/tagger_pixai.py
procslib/models/tagger_wdv3_timm.py
procslib/py.typed
procslib/utils/__init__.py
procslib/utils/hf_utils.py
procslib/utils/lazy_module.py
procslib/utils/simsiam_utils.py
procslib/utils/utils.py
procslib-0.7.1.dist-info/RECORD
