Metadata-Version: 2.1
Name: procslib
Version: 0.7.1
Summary: Multi-purpose processing library for downstream use
Author-Email: yada <trojblue@gmail.com>
License: MIT
Classifier: Development Status :: 4 - Beta
Classifier: Intended Audience :: Developers
Classifier: Programming Language :: Python
Classifier: Programming Language :: Python :: 3
Classifier: Programming Language :: Python :: 3 :: Only
Classifier: Programming Language :: Python :: 3.10
Classifier: Topic :: Documentation
Classifier: Topic :: Software Development
Classifier: Topic :: Utilities
Classifier: Typing :: Typed
Project-URL: Homepage, https://arot-devs.github.io/procslib
Project-URL: Documentation, https://arot-devs.github.io/procslib
Project-URL: Changelog, https://arot-devs.github.io/procslib/changelog
Project-URL: Repository, https://github.com/arot-devs/procslib
Project-URL: Issues, https://github.com/arot-devs/procslib/issues
Project-URL: Discussions, https://github.com/arot-devs/procslib/discussions
Project-URL: Gitter, https://gitter.im/arot-devs/procslib
Project-URL: Funding, https://github.com/sponsors/trojblue
Requires-Python: >=3.10
Requires-Dist: huggingface-hub>=0.29.1
